Google Cloud Platform/__init__.py
Google Cloud Platform/Google BigQuery/TableManagement.py
Google Cloud Platform/Google BigQuery/__init__.py
Google Cloud Platform/Google BigQuery/testingTables.py
InstallationScripts/__init__.py
InstallationScripts/autoGenerateRequirementsText.py
MetaProgramming/__init__.py
metabeaver/__init__.py
metabeaver/get-pip.py
metabeaver/BeaverTown/__init__.py
metabeaver/BeaverTown/abstractBeaver.py
metabeaver/BeaverTown/beaverOn.py
metabeaver/BeaverTown/pumpkinPie.py
metabeaver/Binary/__init__.py
metabeaver/Binary/binaryOperations.py
metabeaver/Caching/LeastRecentlyUsed.py
metabeaver/Caching/__init__.py
metabeaver/DataManipulation/__init__.py
metabeaver/DataManipulation/filterPandas.py
metabeaver/DataManipulation/localPickle.py
metabeaver/DataManipulation/universalResourceLinkHandler.py
metabeaver/DataStructures/BinarySearchTree.py
metabeaver/DataStructures/Node.py
metabeaver/DataStructures/__init__.py
metabeaver/DataStructures/firstInFirstOutQueue.py
metabeaver/DataStructures/firstInLastOut.py
metabeaver/DataStructures/linkedList.py
metabeaver/DatabaseFunctionality/__init__.py
metabeaver/DatabaseFunctionality/SQL/__init__.py
metabeaver/DatabaseFunctionality/SQL/rawSQL.py
metabeaver/DatabaseFunctionality/SQLite/SQLiteDatabase.py
metabeaver/DatabaseFunctionality/SQLite/__init__.py
metabeaver/DatabaseFunctionality/SQLite/commonCreateUpdate.py
metabeaver/DatabaseFunctionality/SQLite/inspectTable.py
metabeaver/DatesAndTime/__init__.py
metabeaver/DatesAndTime/dateAndTimeFundamentals.py
metabeaver/DatesAndTime/getToday.py
metabeaver/Dynamic Programming/__init__.py
metabeaver/FileIO/__init__.py
metabeaver/FileIO/pickleObject.py
metabeaver/FileIO/renameFiles.py
metabeaver/FileIO/yamlIO.py
metabeaver/Formatting/__init__.py
metabeaver/Formatting/printControl.py
metabeaver/Formatting/printControlTest.py
metabeaver/Google Cloud Platform/__init__.py
metabeaver/Google Cloud Platform/Google BigQuery/TableManagement.py
metabeaver-0.5.8.dist-info/METADATA
metabeaver-0.5.8.dist-info/WHEEL
metabeaver-0.5.8.dist-info/top_level.txt
metabeaver-0.5.8.dist-info/RECORD
